docketanalyzer_ocr/__init__.py
docketanalyzer_ocr/document.py
docketanalyzer_ocr/layout.py
docketanalyzer_ocr/ocr.py
docketanalyzer_ocr/remote.py
docketanalyzer_ocr/utils.py
docketanalyzer_ocr-0.1.9.dist-info/METADATA
docketanalyzer_ocr-0.1.9.dist-info/WHEEL
docketanalyzer_ocr-0.1.9.dist-info/licenses/LICENSE
docketanalyzer_ocr-0.1.9.dist-info/RECORD
