Metadata-Version: 2.4
Name: docketanalyzer-ocr
Version: 0.1.9
Summary: Docket Analyzer OCR Utility
Author: Nathan Dahlberg
License-File: LICENSE
Requires-Python: >=3.10
Requires-Dist: dill
Requires-Dist: docketanalyzer-core>=0.1.11
Requires-Dist: doclayout-yolo
Requires-Dist: fastapi
Requires-Dist: huggingface-hub
Requires-Dist: pymupdf
Requires-Dist: runpod
Requires-Dist: surya-ocr
Requires-Dist: uv
Requires-Dist: uvicorn
Provides-Extra: dev
Requires-Dist: docketanalyzer-core[dev]>=0.1.11; extra == 'dev'
